imapidle.py
utils.py
pymap_copy-1.0.2.data/scripts/pymap-copy.py
pymap_copy-1.0.2.dist-info/LICENSE.txt
pymap_copy-1.0.2.dist-info/METADATA
pymap_copy-1.0.2.dist-info/WHEEL
pymap_copy-1.0.2.dist-info/top_level.txt
pymap_copy-1.0.2.dist-info/RECORD
