Metadata-Version: 2.1
Name: pymap-copy
Version: 1.0.2
Summary: Copy and transfer IMAP mailboxes
Home-page: https://github.com/Schluggi/pymap-copy
Author: Lukas Schulte-Tickmann
Author-email: github@das-it-gesicht.de
License: UNKNOWN
Project-URL: Source, https://github.com/Schluggi/pymap-copy
Project-URL: Tracker, https://github.com/Schluggi/pymap-copy/issues
Project-URL: Funding, https://www.paypal.com/cgi-bin/webscr?cmd=_s-xclick&hosted_button_id=KPG2MY37LCC24&source=url
Platform: UNKNOWN
Classifier: Development Status :: 5 - Production/Stable
Classifier: Environment :: Console
Classifier: License :: OSI Approved :: MIT License
Classifier: Operating System :: OS Independent
Classifier: Programming Language :: Python :: 3
Classifier: Topic :: Communications :: Email :: Post-Office :: IMAP
Classifier: Topic :: Utilities
Requires-Python: >=3.6
License-File: LICENSE.txt
Requires-Dist: chardet
Requires-Dist: IMAPClient
Requires-Dist: six
